nzalchemy/__init__.py
nzalchemy/base.py
nzalchemy/nzpy.py
nzalchemy/pyodbc.py
nzalchemy/requirements.py
nzalchemy-11.0.2.dist-info/METADATA
nzalchemy-11.0.2.dist-info/WHEEL
nzalchemy-11.0.2.dist-info/entry_points.txt
nzalchemy-11.0.2.dist-info/top_level.txt
nzalchemy-11.0.2.dist-info/RECORD
