Metadata-Version: 2.1
Name: nzalchemy
Version: 11.0.2
Summary: Netezza Dialect for SQLAlchemy
Home-page: https://github.com/IBM/nzalchemy
Author: 
Author-email: 
License: IBM
Project-URL: Documentation, https://github.com/IBM/nzalchemy/wiki
Project-URL: Source, https://github.com/IBM/nzalchemy
Project-URL: Tracker, https://github.com/IBM/nzalchemy/issues
Keywords: SQLAlchemy IBM nz
Platform: UNKNOWN
Classifier: Development Status :: 5 - Production/Stable
Classifier: Intended Audience :: Developers
Classifier: Programming Language :: Python
Classifier: Programming Language :: Python :: 3
Classifier: Programming Language :: Python :: Implementation :: CPython
Classifier: Topic :: Database :: Front-Ends
Classifier: Operating System :: OS Independent
Requires-Dist: SQLAlchemy (<=1.3.24)
Requires-Dist: nzpy
